mcp_data_analyzer/__init__.py
mcp_data_analyzer/__main__.py
mcp_data_analyzer/cli.py
mcp_data_analyzer/core.py
zhongyiares_mcp_data_analyzer-0.8.dist-info/METADATA
zhongyiares_mcp_data_analyzer-0.8.dist-info/WHEEL
zhongyiares_mcp_data_analyzer-0.8.dist-info/entry_points.txt
zhongyiares_mcp_data_analyzer-0.8.dist-info/top_level.txt
zhongyiares_mcp_data_analyzer-0.8.dist-info/RECORD
