Metadata-Version: 2.4
Name: zhongyiares-mcp-data-analyzer
Version: 0.8
Summary: Add your description here
Requires-Python: >=3.13
Requires-Dist: mcp[cli]>=1.6.0
Requires-Dist: pandas>=2.2.3
Requires-Dist: seaborn>=0.13.2
Requires-Dist: twine>=6.1.0
Requires-Dist: openpyxl>=3.1.5
